disnake/ext/i18n/__init__.py
disnake/ext/i18n/agent.py
disnake/ext/i18n/cache.py
disnake/ext/i18n/language.py
disnake/ext/i18n/preprocess.py
disnake_ext_i18n-0.0.8.dist-info/LICENSE
disnake_ext_i18n-0.0.8.dist-info/METADATA
disnake_ext_i18n-0.0.8.dist-info/WHEEL
disnake_ext_i18n-0.0.8.dist-info/top_level.txt
disnake_ext_i18n-0.0.8.dist-info/RECORD
