Metadata-Version: 2.1
Name: disnake-ext-i18n
Version: 0.0.8
Summary: A forked Disnake extension to support automatic text translations in 107 languages.
Author: Rickaym
Project-URL: Homepage, https://github.com/Rickaym/discord-ext-i18n
Project-URL: Bug Tracker, https://github.com/Rickaym/discord-ext-i18n/issues
Classifier: Intended Audience :: Developers
Classifier: License :: OSI Approved :: MIT License
Classifier: Operating System :: OS Independent
Classifier: Natural Language :: English
Classifier: Programming Language :: Python :: 3.7
Classifier: Programming Language :: Python :: 3.10
Classifier: Programming Language :: Python :: 3.11
Requires-Python: >=3.7
License-File: LICENSE
